mongodb_connect/__init__.py
mongodb_connect/mongo_crud.py
mongodatabaseconnnect-0.0.1.dist-info/METADATA
mongodatabaseconnnect-0.0.1.dist-info/WHEEL
mongodatabaseconnnect-0.0.1.dist-info/top_level.txt
mongodatabaseconnnect-0.0.1.dist-info/RECORD
