Metadata-Version: 2.1
Name: mongodatabaseconnnect
Version: 0.0.1
Summary: A Python package to connect to MongoDB
Home-page: https://github.com/kowshik24/mongodb-connect
Author: kowshik24
Author-email: kowshikcseruet1998@gmail.com
License: MIT
Project-URL: Bug Tracker, https://github.com/kowshik24/mongodb-connect/issues
Classifier: Programming Language :: Python :: 3.7
Classifier: Programming Language :: Python :: 3.8
Classifier: Programming Language :: Python :: 3.9
Classifier: Operating System :: OS Independent
Requires-Python: >=3.7
Requires-Dist: pymongo
Requires-Dist: pymongo[srv]
Requires-Dist: dnspython
Requires-Dist: pandas
Requires-Dist: numpy
Requires-Dist: ensure
Requires-Dist: pytest ==7.1.3
Requires-Dist: tox ==4.15.0
Requires-Dist: black ==22.8.0
Requires-Dist: flake8 ==5.0.4
Requires-Dist: mypy ==0.971
Provides-Extra: testing
Requires-Dist: pytest >=7.1.3 ; extra == 'testing'
Requires-Dist: mypy >=0.971 ; extra == 'testing'
Requires-Dist: flake8 >=5.0.4 ; extra == 'testing'
Requires-Dist: tox ==4.15.0 ; extra == 'testing'
Requires-Dist: black >=22.8.0 ; extra == 'testing'
